mpvsilence.py
mpv_silence-0.1.4.dist-info/METADATA
mpv_silence-0.1.4.dist-info/WHEEL
mpv_silence-0.1.4.dist-info/top_level.txt
mpv_silence-0.1.4.dist-info/RECORD
